ampel/nuclear/flexfit/flex_metrics.py
ampel/nuclear/flexfit/flexfit.py
ampel/nuclear/t0/GaiaVeto.py
ampel/nuclear/t0/NuclearFilter.py
ampel/nuclear/t2/T2FlexFit.py
ampel/nuclear/t2/T2SimpleMetrics.py
ampel/nuclear/t3/T3MetricsPlots.py
ampel/nuclear/t3/T3PlotNeoWISE.py
ampel/nuclear/t3/T3Ranking.py
ampel/nuclear/t3/T3SummaryPlots.py
ampel/nuclear/t3/classifyme.py
ampel/nuclear/t3/dropboxIO.py
ampel/nuclear/test/ZTF20aaaaflr_transientview.pickle
ampel/nuclear/test/ZTF20aaadtjq_flexresult.json
ampel/nuclear/test/ZTF20aaadtjq_simpleresult.json
ampel/nuclear/test/ZTF20aaadtjq_transientview.pickle
ampel/nuclear/test/ZTF20aaadtjq_wisedump.json
ampel/nuclear/test/test_T2_units.py
ampel/nuclear/test/test_T3_units.py
ampel/nuclear/test/test_config.py
ampel/nuclear/test/transientview_list.pickle
conf/ampel-nuclear/channel/TDE_RANKING.yaml
conf/ampel-nuclear/unit.yaml
ampel_nuclear-0.8.3.dist-info/LICENSE
ampel_nuclear-0.8.3.dist-info/METADATA
ampel_nuclear-0.8.3.dist-info/WHEEL
ampel_nuclear-0.8.3.dist-info/RECORD
