Metadata-Version: 2.1
Name: ampel-nuclear
Version: 0.8.3
Summary: Astronomy units for the Ampel system to analyze nuclear events like TDEs
Home-page: https://ampelproject.github.io
License: BSD-3-Clause
Author: Valery Brinnel
Requires-Python: >=3.10,<3.11
Classifier: Development Status :: 4 - Beta
Classifier: Intended Audience :: Science/Research
Classifier: License :: OSI Approved :: BSD License
Classifier: Programming Language :: Python :: 3
Classifier: Programming Language :: Python :: 3.10
Classifier: Topic :: Scientific/Engineering :: Information Analysis
Classifier: Typing :: Typed
Requires-Dist: ampel-hu-astro[slack,sncosmo] (>=0.8.3a10,<0.8.4)
Requires-Dist: ampel-interface (>=0.8.7,<0.9.0)
Requires-Dist: ampel-ztf (>=0.8.4,<0.8.5)
Requires-Dist: corner (>=2.2.1,<3.0.0)
Requires-Dist: dropbox (>=11.36.0,<12.0.0)
Project-URL: Repository, https://github.com/AmpelProject/Ampel-nuclear
